promptxform/__init__.py
promptxform/main.py
promptxform/prompts.py
promptxform-2025.12.21085416.dist-info/METADATA
promptxform-2025.12.21085416.dist-info/WHEEL
promptxform-2025.12.21085416.dist-info/top_level.txt
promptxform-2025.12.21085416.dist-info/RECORD
